cloudpassage/__init__.py
cloudpassage/agent_upgrade.py
cloudpassage/alert_profile.py
cloudpassage/api_key_manager.py
cloudpassage/configuration_policy.py
cloudpassage/container.py
cloudpassage/container_event.py
cloudpassage/container_image.py
cloudpassage/container_package.py
cloudpassage/container_process.py
cloudpassage/csp_accounts.py
cloudpassage/csp_findings.py
cloudpassage/csp_resources.py
cloudpassage/csp_scanner_settings.py
cloudpassage/cve_details.py
cloudpassage/cve_exception.py
cloudpassage/event.py
cloudpassage/exceptions.py
cloudpassage/fim_policy.py
cloudpassage/firewall_policy.py
cloudpassage/halo.py
cloudpassage/halo_endpoint.py
cloudpassage/http_helper.py
cloudpassage/image_issue.py
cloudpassage/image_registry.py
cloudpassage/image_repo.py
cloudpassage/issue.py
cloudpassage/lids_policy.py
cloudpassage/local_user_account.py
cloudpassage/local_user_group.py
cloudpassage/sanity.py
cloudpassage/scan.py
cloudpassage/server.py
cloudpassage/server_group.py
cloudpassage/special_events_policy.py
cloudpassage/system_announcement.py
cloudpassage/time_series.py
cloudpassage/utility.py
cloudpassage-1.6.5.dist-info/LICENSE.txt
cloudpassage-1.6.5.dist-info/METADATA
cloudpassage-1.6.5.dist-info/WHEEL
cloudpassage-1.6.5.dist-info/top_level.txt
cloudpassage-1.6.5.dist-info/RECORD
