Metadata-Version: 2.1
Name: cloudpassage
Version: 1.6.5
Summary: Python SDK for CloudPassage Halo API
Home-page: http://github.com/cloudpassage/cloudpassage-halo-python-sdk
Author: CloudPassage
Author-email: toolbox@cloudpassage.com
License: BSD
Keywords: cloudpassage halo api sdk
Platform: UNKNOWN
Classifier: Development Status :: 5 - Production/Stable
Classifier: Intended Audience :: Developers
Classifier: Operating System :: MacOS :: MacOS X
Classifier: Operating System :: POSIX :: Linux
Classifier: Programming Language :: Python :: 2.7
Classifier: Programming Language :: Python :: 3.6
Classifier: Programming Language :: Python :: 3.7
Classifier: Topic :: Security
Classifier: License :: OSI Approved :: BSD License
Requires-Dist: pyaml
Requires-Dist: requests (>=2.18)
